{
    "鐵之眼": [
        {
            "等級": 1,
            "生命力": 6,
            "集中力": 2,
            "耐力": 4,
            "力氣": 4,
            "敏捷": 8,
            "智力": 2,
            "信仰": 2,
            "感應": 13,
            "總點數": 41,
            "增加點數": 0,
            "HP": 200,
            "FP": 55,
            "ST": 56
        },
        {
            "等級": 2,
            "生命力": 12,
            "集中力": 3,
            "耐力": 7,
            "力氣": 7,
            "敏捷": 20,
            "智力": 3,
            "信仰": 3,
            "感應": 13,
            "總點數": 68,
            "增加點數": 27,
            "HP": 320,
            "FP": 60,
            "ST": 62
        },
        {
            "等級": 3,
            "生命力": 14,
            "集中力": 3,
            "耐力": 8,
            "力氣": 8,
            "敏捷": 23,
            "智力": 3,
            "信仰": 3,
            "感應": 13,
            "總點數": 75,
            "增加點數": 7,
            "HP": 360,
            "FP": 60,
            "ST": 64
        },
        {
            "等級": 4,
            "生命力": 16,
            "集中力": 4,
            "耐力": 10,
            "力氣": 9,
            "敏捷": 26,
            "智力": 3,
            "信仰": 4,
            "感應": 13,
            "總點數": 85,
            "增加點數": 10,
            "HP": 400,
            "FP": 65,
            "ST": 68
        },
        {
            "等級": 5,
            "生命力": 18,
            "集中力": 5,
            "耐力": 12,
            "力氣": 10,
            "敏捷": 29,
            "智力": 3,
            "信仰": 5,
            "感應": 13,
            "總點數": 95,
            "增加點數": 10,
            "HP": 440,
            "FP": 70,
            "ST": 72
        },
        {
            "等級": 6,
            "生命力": 20,
            "集中力": 6,
            "耐力": 14,
            "力氣": 11,
            "敏捷": 32,
            "智力": 4,
            "信仰": 5,
            "感應": 13,
            "總點數": 105,
            "增加點數": 10,
            "HP": 480,
            "FP": 75,
            "ST": 76
        },
        {
            "等級": 7,
            "生命力": 23,
            "集中力": 7,
            "耐力": 16,
            "力氣": 12,
            "敏捷": 35,
            "智力": 4,
            "信仰": 6,
            "感應": 13,
            "總點數": 116,
            "增加點數": 11,
            "HP": 540,
            "FP": 80,
            "ST": 80
        },
        {
            "等級": 8,
            "生命力": 25,
            "集中力": 7,
            "耐力": 17,
            "力氣": 13,
            "敏捷": 38,
            "智力": 4,
            "信仰": 7,
            "感應": 13,
            "總點數": 124,
            "增加點數": 8,
            "HP": 580,
            "FP": 80,
            "ST": 82
        },
        {
            "等級": 9,
            "生命力": 27,
            "集中力": 8,
            "耐力": 19,
            "力氣": 14,
            "敏捷": 41,
            "智力": 5,
            "信仰": 7,
            "感應": 13,
            "總點數": 134,
            "增加點數": 10,
            "HP": 620,
            "FP": 85,
            "ST": 86
        },
        {
            "等級": 10,
            "生命力": 29,
            "集中力": 9,
            "耐力": 21,
            "力氣": 15,
            "敏捷": 44,
            "智力": 5,
            "信仰": 8,
            "感應": 13,
            "總點數": 144,
            "增加點數": 10,
            "HP": 660,
            "FP": 90,
            "ST": 90
        },
        {
            "等級": 11,
            "生命力": 31,
            "集中力": 10,
            "耐力": 23,
            "力氣": 16,
            "敏捷": 47,
            "智力": 5,
            "信仰": 9,
            "感應": 13,
            "總點數": 154,
            "增加點數": 10,
            "HP": 700,
            "FP": 95,
            "ST": 94
        },
        {
            "等級": 12,
            "生命力": 34,
            "集中力": 11,
            "耐力": 25,
            "力氣": 17,
            "敏捷": 51,
            "智力": 6,
            "信仰": 10,
            "感應": 13,
            "總點數": 167,
            "增加點數": 13,
            "HP": 760,
            "FP": 100,
            "ST": 98
        },
        {
            "等級": 13,
            "生命力": 35,
            "集中力": 12,
            "耐力": 26,
            "力氣": 17,
            "敏捷": 53,
            "智力": 6,
            "信仰": 11,
            "感應": 13,
            "總點數": 173,
            "增加點數": 6,
            "HP": 780,
            "FP": 105,
            "ST": 100
        },
        {
            "等級": 14,
            "生命力": 36,
            "集中力": 13,
            "耐力": 27,
            "力氣": 18,
            "敏捷": 55,
            "智力": 6,
            "信仰": 12,
            "感應": 13,
            "總點數": 180,
            "增加點數": 7,
            "HP": 800,
            "FP": 110,
            "ST": 102
        },
        {
            "等級": 15,
            "生命力": 37,
            "集中力": 14,
            "耐力": 28,
            "力氣": 19,
            "敏捷": 57,
            "智力": 7,
            "信仰": 13,
            "感應": 13,
            "總點數": 188,
            "增加點數": 8,
            "HP": 820,
            "FP": 115,
            "ST": 104
        }
    ]
}